plantpy/__init__.py
plantpy/plantpy.py
plantpy-0.0.4.dist-info/LICENSE
plantpy-0.0.4.dist-info/METADATA
plantpy-0.0.4.dist-info/WHEEL
plantpy-0.0.4.dist-info/entry_points.txt
plantpy-0.0.4.dist-info/top_level.txt
plantpy-0.0.4.dist-info/RECORD
