Metadata-Version: 2.1
Name: plantpy
Version: 0.0.4
Summary: Plant Village Survey Export: Simple CLI
Home-page: https://github.com/samapriya/plantpy
Author: Samapriya Roy
Author-email: samapriya.roy@gmail.com
License: Apache 2.0
Platform: UNKNOWN
Classifier: Development Status :: 3 - Alpha
Classifier: Intended Audience :: Developers
Classifier: Intended Audience :: Science/Research
Classifier: Natural Language :: English
Classifier: License :: OSI Approved :: Apache Software License
Classifier: Programming Language :: Python :: 3
Classifier: Programming Language :: Python :: 3.6
Classifier: Programming Language :: Python :: 3.7
Classifier: Programming Language :: Python :: 3.8
Classifier: Operating System :: OS Independent
Classifier: Topic :: Scientific/Engineering :: GIS
Requires-Python: >=3.2
Requires-Dist: rapidfuzz (>=0.2.2)
Requires-Dist: requests (>=2.23.0)
Requires-Dist: beautifulsoup4 (>=4.9.1)
Requires-Dist: pandas (>=1.0.3)
Requires-Dist: shapely (>=1.7.0) ; platform_system != "Windows"
Requires-Dist: geopandas (>=0.7.0) ; platform_system != "Windows"
